test0014/__init__.py
test0014-2.0.dist-info/DESCRIPTION.rst
test0014-2.0.dist-info/METADATA
test0014-2.0.dist-info/RECORD
test0014-2.0.dist-info/WHEEL
test0014-2.0.dist-info/metadata.json
test0014-2.0.dist-info/top_level.txt
