Metadata-Version: 2.0
Name: test0014
Version: 2.0
Summary: Testing something
Home-page: UNKNOWN
Author: Tector Pro
Author-email: UNKNOWN
License: UNKNOWN
Platform: UNKNOWN
Requires-Dist: Abhi-pdf (==1.1)
